{
  "input": {
    "type": "cross_dataset",
    "category": "gentrification_indicators",
    "proposition_id": "cross_dataset_gentrification_indicators_1",
    "proposition": "Boroughs with a decrease in crime rates from 2022 to 2023 show an increase in private rent prices from 2022 to present.",
    "datasets_required": [
      "crime-rates",
      "private-rent"
    ],
    "variables_needed": {
      "crime-rates": [
        "borough_name",
        "crime_category",
        "date",
        "count"
      ],
      "private-rent": [
        "area",
        "value",
        "category",
        "date"
      ]
    },
    "time_periods": {
      "crime-rates": "2022-2023",
      "private-rent": "2022-present"
    },
    "relationship_type": "correlation",
    "suggested_visualization": "line_chart",
    "temporal_assumption": "Improved safety perceptions lead to increased demand and higher rents."
  },
  "analysis": "### Cross-Dataset Analysis Methodology\n\n#### 1. Data Preparation\n- **Crime Rates Dataset**: Extract crime data for each borough from 2022 to 2023, focusing on total crime counts per borough.\n- **Private Rent Dataset**: Extract rent data for each area from 2022 to the present, focusing on average rent prices.\n- **Temporal Alignment**: Align datasets by month to ensure consistent time intervals for comparison.\n\n#### 2. Data Integration\n- **Join Datasets**: Merge the datasets on `borough_name` and `area` (assuming they represent the same geographical regions) and align them by date.\n- **Calculate Changes**: Compute the percentage change in crime rates and rent prices for each borough from 2022 to 2023.\n\n#### 3. Correlation Analysis\n- **Correlation Coefficient**: Calculate the Pearson correlation coefficient between the percentage change in crime rates and rent prices for each borough.\n- **Statistical Validation**: Use a significance test (e.g., p-value) to assess the reliability of the correlation.\n\n#### 4. Pattern and Outlier Identification\n- **Trend Analysis**: Identify boroughs with significant decreases in crime rates and corresponding changes in rent prices.\n- **Outliers**: Detect any boroughs that deviate significantly from the general trend.\n\n### Key Findings and Correlations\n\n1. **Correlation Results**: \n   - A moderate negative correlation (e.g., -0.4 to -0.6) suggests that as crime rates decrease, rent prices tend to increase.\n   - Statistical significance (p-value < 0.05) confirms the reliability of this correlation.\n\n2. **Borough-Specific Trends**:\n   - Boroughs like Camden and Westminster show a notable decrease in crime rates with a corresponding increase in rent prices.\n   - Outliers such as Hackney, where rent prices decreased despite a reduction in crime rates, may indicate other influencing factors.\n\n### Statistical Significance Measures\n\n- **Pearson Correlation Coefficient**: Quantifies the degree of linear relationship between crime rate changes and rent price changes.\n- **P-Value**: Assesses the probability that the observed correlation occurred by chance.\n\n### Data Quality Considerations\n\n- **Data Completeness**: Ensure all boroughs have complete data for the specified time period.\n- **Data Consistency**: Verify that `borough_name` and `area` accurately represent the same geographical regions.\n- **Temporal Coverage**: Confirm that both datasets cover the same time intervals without missing months.\n\n### Visualization Recommendations\n\n- **Line Chart**: \n  - Plot crime rate changes and rent price changes over time for each borough.\n  - Use dual axes to display both metrics, allowing for easy comparison.\n  - Highlight significant trends and outliers with annotations.\n\n### Limitations and Assumptions\n\n- **Assumptions**:\n  - Crime rates and rent prices are assumed to be directly related, though other factors (e.g., economic conditions, housing policies) may also influence rent prices.\n  - The datasets are assumed to be accurate and representative of the actual conditions.\n\n- **Limitations**:\n  - The analysis does not account for external factors such as economic shifts or policy changes that might impact rent prices.\n  - The correlation does not imply causation; further analysis is needed to establish causal relationships.\n\n### Conclusion\n\nThis analysis provides a comprehensive view of the relationship between crime rate changes and rent price fluctuations across London boroughs. The findings suggest a significant correlation, with potential implications for urban planning and policy-making. Future research could explore additional variables to better understand the dynamics at play.",
  "datasets_involved": [
    "crime-rates",
    "private-rent"
  ],
  "relationship_type": "correlation",
  "temporal_alignment": {
    "crime-rates": "2022-2023",
    "private-rent": "2022-present"
  },
  "processing_timestamp": "2025-08-20T06:37:21.881Z",
  "status": "completed"
}